LICENSE
MANIFEST.in
README.md
setup.py
dash_pdf_highlighter/257.dash_pdf_highlighter.js
dash_pdf_highlighter/PdfViewer.py
dash_pdf_highlighter/__init__.py
dash_pdf_highlighter/_imports_.py
dash_pdf_highlighter/dash_pdf_highlighter.js
dash_pdf_highlighter/metadata.json
dash_pdf_highlighter/package-info.json
dash_pdf_highlighter/proptypes.js
dash_pdf_highlighter.egg-info/PKG-INFO
dash_pdf_highlighter.egg-info/SOURCES.txt
dash_pdf_highlighter.egg-info/dependency_links.txt
dash_pdf_highlighter.egg-info/top_level.txt
dash_pdf_highlighter/segmenter/__init__.py
dash_pdf_highlighter/segmenter/base.py
dash_pdf_highlighter/segmenter/figure.py
dash_pdf_highlighter/segmenter/mongo.py
dash_pdf_highlighter/segmenter/semantic.py
dash_pdf_highlighter/segmenter/sentence.py
dash_pdf_highlighter_base/__init__.py
dash_pdf_highlighter_base/segmenter/__init__.py
dash_pdf_highlighter_base/segmenter/base.py
dash_pdf_highlighter_base/segmenter/figure.py
dash_pdf_highlighter_base/segmenter/mongo.py
dash_pdf_highlighter_base/segmenter/semantic.py
dash_pdf_highlighter_base/segmenter/sentence.py