Metadata-Version: 2.1
Name: dash-pdf-highlighter
Version: 0.0.7
Summary: Components to view PDFs and edit and show highlighted regions
Author: Viktor Krückl <viktor@krueckl.de>
License: MIT
Classifier: Framework :: Dash
License-File: LICENSE
